fastmcp_feedback/__init__.py
fastmcp_feedback/database.py
fastmcp_feedback/feedback.py
fastmcp_feedback/insights.py
fastmcp_feedback/models.py
fastmcp_feedback/tools.py
fastmcp_feedback/mixins/__init__.py
fastmcp_feedback/mixins/base.py
fastmcp_feedback/mixins/management.py
fastmcp_feedback/mixins/retrieval.py
fastmcp_feedback/mixins/submission.py
fastmcp_feedback-2026.1.12.1.dist-info/METADATA
fastmcp_feedback-2026.1.12.1.dist-info/WHEEL
fastmcp_feedback-2026.1.12.1.dist-info/licenses/LICENSE
fastmcp_feedback-2026.1.12.1.dist-info/RECORD
