Metadata-Version: 2.4
Name: fastmcp-feedback
Version: 2026.1.12.1
Summary: Production-ready feedback collection system for FastMCP servers
Project-URL: Homepage, https://git.supported.systems/fastmcp-feedback/fastmcp-feedback
Project-URL: Documentation, https://fastmcp-feedback.l.supported.systems
Project-URL: Repository, https://git.supported.systems/fastmcp-feedback/fastmcp-feedback.git
Project-URL: Issues, https://git.supported.systems/fastmcp-feedback/fastmcp-feedback/issues
Project-URL: Changelog, https://git.supported.systems/fastmcp-feedback/fastmcp-feedback/blob/main/CHANGELOG.md
Author-email: Ryan Malloy <ryan@supported.systems>
Maintainer-email: Ryan Malloy <ryan@supported.systems>
License-Expression: MIT
License-File: LICENSE
Keywords: analytics,database,enterprise,fastmcp,feedback,mcp,model-context-protocol,privacy-compliant,server
Classifier: Development Status :: 5 - Production/Stable
Classifier: Intended Audience :: Developers
Classifier: License :: OSI Approved :: MIT License
Classifier: Operating System :: OS Independent
Classifier: Programming Language :: Python
Classifier: Programming Language :: Python :: 3
Classifier: Programming Language :: Python :: 3.11
Classifier: Programming Language :: Python :: 3.12
Classifier: Programming Language :: Python :: 3.13
Classifier: Topic :: Database :: Database Engines/Servers
Classifier: Topic :: Software Development :: Libraries :: Python Modules
Classifier: Topic :: System :: Logging
Classifier: Topic :: System :: Monitoring
Classifier: Typing :: Typed
Requires-Python: >=3.11
Requires-Dist: fastmcp>=2.12.2
Requires-Dist: pydantic>=2.11.7
Requires-Dist: sqlalchemy>=2.0.43
Provides-Extra: all
Requires-Dist: mypy>=1.7.0; extra == 'all'
Requires-Dist: psycopg2-binary>=2.9.0; extra == 'all'
Requires-Dist: pymysql>=1.1.0; extra == 'all'
Requires-Dist: pytest-asyncio>=0.23.0; extra == 'all'
Requires-Dist: pytest-cov>=5.0.0; extra == 'all'
Requires-Dist: pytest-mock>=3.12.0; extra == 'all'
Requires-Dist: pytest>=8.2.0; extra == 'all'
Requires-Dist: ruff>=0.1.0; extra == 'all'
Provides-Extra: dev
Requires-Dist: mypy>=1.7.0; extra == 'dev'
Requires-Dist: pytest-asyncio>=0.23.0; extra == 'dev'
Requires-Dist: pytest-cov>=5.0.0; extra == 'dev'
Requires-Dist: pytest-mock>=3.12.0; extra == 'dev'
Requires-Dist: pytest>=8.2.0; extra == 'dev'
Requires-Dist: ruff>=0.1.0; extra == 'dev'
Provides-Extra: mysql
Requires-Dist: pymysql>=1.1.0; extra == 'mysql'
Provides-Extra: postgresql
Requires-Dist: psycopg2-binary>=2.9.0; extra == 'postgresql'
Provides-Extra: test
Requires-Dist: pytest-asyncio>=0.23.0; extra == 'test'
Requires-Dist: pytest-cov>=5.0.0; extra == 'test'
Requires-Dist: pytest-mock>=3.12.0; extra == 'test'
Requires-Dist: pytest>=8.2.0; extra == 'test'
